electrumsv_database/__init__.py
electrumsv_database/py.typed
electrumsv_database/sqlite.py
electrumsv_database-1.7.dist-info/LICENSE
electrumsv_database-1.7.dist-info/METADATA
electrumsv_database-1.7.dist-info/WHEEL
electrumsv_database-1.7.dist-info/top_level.txt
electrumsv_database-1.7.dist-info/RECORD
