Metadata-Version: 2.1
Name: electrumsv-database
Version: 1.7
Summary: Database support for use of SQLite (possibly other databases later).
Home-page: https://github.com/electrumsv/electrumsv-database
Author: Roger Taylor
Author-email: roger.taylor.email@gmail.com
License: MIT license
License-File: LICENSE
Requires-Dist: pysqlite3-binary ; platform_system == "Linux"
